{"cameraMode":{"drawMode":0,"name":"Shaded","section":"Shading Mode"},"sceneLighting":false,"audioPlay":false,"sceneViewState":{"m_AlwaysRefresh":false,"showFog":true,"showSkybox":true,"showFlares":true,"showImageEffects":true,"showParticleSystems":true,"showVisualEffectGraphs":true,"m_FxEnabled":true},"in2DMode":false,"pivot":{"x":6.641871929168701,"y":3.9269888401031496,"z":5.679014682769775},"rotation":{"x":0.1016223132610321,"y":-0.8782047033309937,"z":0.21491223573684693,"w":0.4151654839515686},"size":0.6495208144187927,"orthographic":false}